bitbitbot/__init__.py
bitbitbot/bot.py
bitbitbot/commands.py
bitbitbot/events.py
bitbitbot/main.py
bitbitbot/models.py
bitbitbot/parsers/__init__.py
bitbitbot/parsers/plugins/__init__.py
bitbitbot/parsers/plugins/_install.py
bitbitbot/parsers/plugins/plugins.py
bitbitbot/parsers/run/__init__.py
bitbitbot/parsers/run/run.py
bitbitbot-0.0.10.dist-info/LICENSE.txt
bitbitbot-0.0.10.dist-info/METADATA
bitbitbot-0.0.10.dist-info/WHEEL
bitbitbot-0.0.10.dist-info/entry_points.txt
bitbitbot-0.0.10.dist-info/top_level.txt
bitbitbot-0.0.10.dist-info/RECORD
