Metadata-Version: 2.1
Name: bitbitbot
Version: 0.0.10
Summary: An unopionated, extensible Twitch Chat Bot
Home-page: https://github.com/MetaBytez/bitbitbot
Author: William Johns
Author-email: will@wcj.dev
License: UNKNOWN
Platform: UNKNOWN
Classifier: License :: OSI Approved :: MIT License
Classifier: Programming Language :: Python :: 3
Classifier: Programming Language :: Python :: 3.9
Requires-Dist: irc
Requires-Dist: pydantic
